README.md
setup.cfg
setup.py
aws_hat/__init__.py
aws_hat/helpers.py
aws_hat/main.py
aws_hat.egg-info/PKG-INFO
aws_hat.egg-info/SOURCES.txt
aws_hat.egg-info/dependency_links.txt
aws_hat.egg-info/entry_points.txt
aws_hat.egg-info/top_level.txt